sdk/__init__.py
sdk/guardrails.py
sdk/guardrails_config.py
sdk/red_team.py
enkryptai-0.1.0.dist-info/LICENSE
enkryptai-0.1.0.dist-info/METADATA
enkryptai-0.1.0.dist-info/WHEEL
enkryptai-0.1.0.dist-info/top_level.txt
enkryptai-0.1.0.dist-info/RECORD
